Metadata-Version: 2.1
Name: debuggingbook
Version: 1.3
Summary: Code for 'The Debugging Book' (https://www.debuggingbook.org/)
Home-page: https://www.debuggingbook.org/
Author: Andreas Zeller
Author-email: zeller@cispa.de
Classifier: Development Status :: 5 - Production/Stable
Classifier: Framework :: Jupyter
Classifier: Intended Audience :: Developers
Classifier: Intended Audience :: Education
Classifier: Programming Language :: Python :: 3
Classifier: License :: OSI Approved :: MIT License
Classifier: Operating System :: OS Independent
Classifier: Topic :: Software Development :: Debuggers
Classifier: Topic :: Software Development :: Testing
Classifier: Topic :: Education :: Testing
Classifier: Topic :: Software Development :: Quality Assurance
Classifier: Topic :: Security
Requires-Python: >=3.10
Requires-Dist: beautifulsoup4>=4.9.3
Requires-Dist: diff_match_patch>=20200713
Requires-Dist: easyplotly>=0.1.3
Requires-Dist: enforce>=0.3.4
Requires-Dist: fuzzingbook>=0.8.1
Requires-Dist: graphviz>=0.14.2
Requires-Dist: ipython>=7.16.1
Requires-Dist: lxml>=4.5.1
Requires-Dist: Markdown>=3.3.4
Requires-Dist: matplotlib>=3.3.2
Requires-Dist: multiprocess>=0.70.12.2
Requires-Dist: nbconvert>=6.0.7
Requires-Dist: nbformat>=5.0.8
Requires-Dist: networkx>=2.5
Requires-Dist: numpy>=2.2.1
Requires-Dist: pandas>=2.2.3
Requires-Dist: pydriller>=2.3
Requires-Dist: pyparsing==2.4.7
Requires-Dist: Pygments>=2.7.1
Requires-Dist: python-magic>=0.4.18
Requires-Dist: scikit_learn>=0.23.2
Requires-Dist: selenium>=3.141.0
